bdsca_analysis_config_file/__init__.py
bdsca_analysis_config_file/__main__.py
bdsca_analysis_config_file/blackduck_remediate_vuln.py
bdsca_analysis_config_file/cli.py
bdsca_analysis_config_file/endpoint_mocks.py
bdsca_analysis_config_file/schema.py
bdsca_analysis_config_file-0.1.13.dist-info/licenses/LICENSE
bdsca_analysis_config_file-0.1.13.dist-info/METADATA
bdsca_analysis_config_file-0.1.13.dist-info/WHEEL
bdsca_analysis_config_file-0.1.13.dist-info/entry_points.txt
bdsca_analysis_config_file-0.1.13.dist-info/top_level.txt
bdsca_analysis_config_file-0.1.13.dist-info/RECORD
