Metadata-Version: 2.4
Name: bdsca-analysis-config-file
Version: 0.1.13
Summary: Tools and CLI for handling BDSCA analysis configuration file(s).
Author: Jouni Lehto
License-Expression: MIT
Project-URL: Homepage, https://example.com/placeholder
Project-URL: Repository, https://example.com/placeholder/repo
Keywords: bdsca,analysis,config,yaml,cli
Classifier: Programming Language :: Python :: 3
Classifier: Programming Language :: Python :: 3 :: Only
Classifier: Operating System :: OS Independent
Requires-Python: >=3.9
License-File: LICENSE
Requires-Dist: PyYAML>=6.0
Requires-Dist: jsonschema>=4.17.0
Provides-Extra: dev
Requires-Dist: pytest>=7.4; extra == "dev"
Requires-Dist: pytest-cov>=4.1; extra == "dev"
Requires-Dist: ruff>=0.5.0; extra == "dev"
Requires-Dist: black>=24.3.0; extra == "dev"
Requires-Dist: mypy>=1.10.0; extra == "dev"
Requires-Dist: types-setuptools>=68.0.0.3; extra == "dev"
Requires-Dist: pre-commit>=3.7.0; extra == "dev"
Dynamic: license-file
